automancy/__init__.py
automancy/core/__init__.py
automancy/core/automancy_chain.py
automancy/core/browser.py
automancy/core/elemental.py
automancy/core/external_javascript.py
automancy/core/ffmpeg_encoders.py
automancy/core/model.py
automancy/core/tactical_asserts.py
automancy/core/wait_for_page_load.py
automancy/decorators/__init__.py
automancy/decorators/deprecated.py
automancy/decorators/interaction.py
automancy/ecosystems/__init__.py
automancy/ecosystems/page.py
automancy/elementals/__init__.py
automancy/elementals/atoms/__init__.py
automancy/elementals/atoms/button.py
automancy/elementals/atoms/checkbox.py
automancy/elementals/atoms/file_input.py
automancy/elementals/atoms/image.py
automancy/elementals/atoms/label.py
automancy/elementals/atoms/link.py
automancy/elementals/atoms/radio.py
automancy/elementals/atoms/svg.py
automancy/elementals/atoms/switch.py
automancy/elementals/atoms/text_input.py
automancy/elementals/molecules/__init__.py
automancy/elementals/molecules/dialogbox.py
automancy/elementals/molecules/form.py
automancy/elementals/molecules/modal.py
automancy/elementals/molecules/slider.py
automancy/elementals/organisms/__init__.py
automancy/elementals/organisms/calendar/__init__.py
automancy/elementals/organisms/calendar/calendar.py
automancy/elementals/organisms/calendar/calendar_day.py
automancy/elementals/organisms/calendar/calendar_month.py
automancy/elementals/organisms/calendar/calendar_month_options.py
automancy/elementals/organisms/calendar/calendar_options.py
automancy/elementals/organisms/calendar/calendar_week.py
automancy/elementals/organisms/clock/__init__.py
automancy/elementals/organisms/clock/clock.py
automancy/elementals/organisms/clock/clock_options.py
automancy/elementals/organisms/dropdown/__init__.py
automancy/elementals/organisms/dropdown/dropdown.py
automancy/elementals/organisms/dropdown/dropdown_options.py
automancy/elementals/organisms/grid/__init__.py
automancy/elementals/organisms/grid/grid.py
Automancy-0.5.12.dist-info/LICENSE
Automancy-0.5.12.dist-info/METADATA
Automancy-0.5.12.dist-info/WHEEL
Automancy-0.5.12.dist-info/top_level.txt
Automancy-0.5.12.dist-info/RECORD
