Metadata-Version: 2.1
Name: Automancy
Version: 0.5.12
Home-page: https://github.com/iamtheblurr/automancy
Author: Jonathan Craig
Author-email: blurr@iamtheblurr.com
License: MIT
Classifier: Programming Language :: Python :: 3.7
Classifier: Programming Language :: Python :: 3.8
Classifier: Programming Language :: Python :: 3.9
Classifier: Programming Language :: Python :: 3.10
Classifier: Topic :: Software Development :: Quality Assurance
Classifier: Topic :: Software Development :: Testing
Classifier: Topic :: Internet :: WWW/HTTP :: Browsers
Requires-Python: >=3.7
License-File: LICENSE
Requires-Dist: chronomancy
Requires-Dist: lxml
Requires-Dist: pytest
Requires-Dist: selenium
Requires-Dist: webvtt-py
